sportmonks/__init__.py
sportmonks/_base.py
sportmonks/_types.py
sportmonks/soccer.py
sportmonks-1.2.0.dist-info/LICENSE
sportmonks-1.2.0.dist-info/METADATA
sportmonks-1.2.0.dist-info/WHEEL
sportmonks-1.2.0.dist-info/top_level.txt
sportmonks-1.2.0.dist-info/RECORD
